{"id":"austin1286-20260714-120357","author":"austin1286","submittedAt":"2026-07-14T04:23:29.0499959+00:00","cpuName":"AMD Ryzen 7 9800X3D","gpuName":"NVIDIA GeForce RTX 5070 Ti","osName":"Microsoft Windows 11 \u4E13\u4E1A\u7248","motherboardName":"\u534E\u7855(ASUS) ROG STRIX B850-A GAMING WIFI S BIOS 1087","memoryInfo":"32 GB | DDR5 | G Skill Intl F5-6000J2836G16G 16 GB 6000 MHz | G Skill Intl F5-6000J2836G16G 16 GB 6000 MHz | \u7A7A | \u7A7A","diskInfo":"WD_BLACK SN850X 2000GB HDD 1863 GB SCSI | KINGSTON SA2000M81000G HDD 931.5 GB SCSI","displayInfo":"\u534E\u7855(ASUS) (SN:TALMTF079974) 2560 x 1440 240 Hz \u4E3B\u663E","gamingScore":222,"gamingGrade":"S","officeScore":137,"officeGrade":"S","cpuSingleCoreScore":97,"cpuMultiCoreScore":87,"gpuRenderScore":424,"memoryCapacityScore":98,"diskSeqReadScore":116,"diskSeqWriteScore":98,"disk4KReadScore":186,"disk4KWriteScore":204,"browserTotalScore":137,"repoPath":"","submittedAtShort":"2026-07-14 12:23"}