{"id":"firecat616-20260720-194259","author":"firecat616","submittedAt":"2026-07-20T12:06:18.8789103+00:00","cpuName":"AMD Ryzen 5 9600X","gpuName":"AMD Radeon RX 7900 XT","osName":"Microsoft Windows 11 \u4E13\u4E1A\u7248 Insider Preview","motherboardName":"\u94ED\u7444(Maxsun) MS-Terminator B850M BIOS B2.4D","memoryInfo":"31.6 GB | DDR5 | Team Group Inc UD5-6400 16 GB 6200 MHz | Team Group Inc UD5-6400 16 GB 6200 MHz | \u7A7A | \u7A7A","diskInfo":"Samsung SSD 980 PRO 1TB HDD 931.5 GB SCSI | KIOXIA-EXCERIA PLUS G3 SSD HDD 931.5 GB SCSI","displayInfo":"XMI (SN:7041310001789) 2560 x 1440 200 Hz \u4E3B\u663E","gamingScore":205,"gamingGrade":"S","officeScore":129,"officeGrade":"A\u002B","cpuSingleCoreScore":108,"cpuMultiCoreScore":70,"gpuRenderScore":386,"memoryCapacityScore":98,"diskSeqReadScore":114,"diskSeqWriteScore":59,"disk4KReadScore":143,"disk4KWriteScore":115,"browserTotalScore":147,"repoPath":"","submittedAtShort":"2026-07-20 20:06"}