{"id":"3804313647-20260713-093902","author":"3804313647","submittedAt":"2026-07-13T01:43:37.9322467+00:00","cpuName":"Genuine Intel 0000","gpuName":"AMD Radeon RX 6600 XT","osName":"Microsoft Windows 11 IoT \u4F01\u4E1A\u7248 LTSC","motherboardName":"\u534E\u7855(ASUS) H170-PLUS D3 BIOS 2604 Reborn by dsanke","memoryInfo":"16 GB | DDR3 | 1316 DDR3 1600MHz  8GB 8 GB 1867 MHz | 1316 DDR3 1600MHz  8GB 8 GB 1867 MHz | \u7A7A | \u7A7A","diskInfo":"WDC WDS100T2B0C-00PXH0 HDD 931.5 GB SCSI","displayInfo":"SKG 2560 x 1440 100 Hz \u4E3B\u663E","gamingScore":111,"gamingGrade":"A\u002B","officeScore":69,"officeGrade":"B\u002B","cpuSingleCoreScore":72,"cpuMultiCoreScore":45,"gpuRenderScore":201,"memoryCapacityScore":49,"diskSeqReadScore":56,"diskSeqWriteScore":16,"disk4KReadScore":80,"disk4KWriteScore":91,"browserTotalScore":73,"repoPath":"","submittedAtShort":"2026-07-13 09:43"}