{"id":"GHOSTCYJ-20260712-235015","author":"GHOSTCYJ","submittedAt":"2026-07-12T15:58:21.1649065+00:00","cpuName":"AMD Ryzen 9 9950X","gpuName":"AMD Radeon RX 9070 XT","osName":"Microsoft Windows 11 \u4E13\u4E1A\u7248","motherboardName":"\u6280\u5609(Gigabyte) B650M AORUS PRO AX BIOS F41a","memoryInfo":"48 GB | DDR5 | Machenike JJ02H0003 24 GB 6000 MHz | Machenike JJ02H0003 24 GB 6000 MHz | \u7A7A | \u7A7A","diskInfo":"HGST HUH721010ALE600 HDD 9314 GB IDE/PATA | HP SSD SP803 2TB HDD 1907.7 GB SCSI | Predator SSD GM7 M.2 2TB HDD 1907.7 GB SCSI","displayInfo":"XMI 3840 x 2160 160 Hz \u4E3B\u663E","gamingScore":267,"gamingGrade":"S","officeScore":150,"officeGrade":"S","cpuSingleCoreScore":100,"cpuMultiCoreScore":193,"gpuRenderScore":517,"memoryCapacityScore":142,"diskSeqReadScore":120,"diskSeqWriteScore":105,"disk4KReadScore":187,"disk4KWriteScore":186,"browserTotalScore":129,"repoPath":"","submittedAtShort":"2026-07-12 23:58"}